wagtail_localize_dashboard/__init__.py
wagtail_localize_dashboard/apps.py
wagtail_localize_dashboard/forms.py
wagtail_localize_dashboard/models.py
wagtail_localize_dashboard/settings.py
wagtail_localize_dashboard/signals.py
wagtail_localize_dashboard/urls.py
wagtail_localize_dashboard/utils.py
wagtail_localize_dashboard/views.py
wagtail_localize_dashboard/wagtail_hooks.py
wagtail_localize_dashboard/management/__init__.py
wagtail_localize_dashboard/management/commands/__init__.py
wagtail_localize_dashboard/management/commands/rebuild_translation_progress.py
wagtail_localize_dashboard/migrations/0001_initial.py
wagtail_localize_dashboard/migrations/__init__.py
wagtail_localize_dashboard/static/wagtail_localize_dashboard/css/dashboard.css
wagtail_localize_dashboard/templates/wagtail_localize_dashboard/dashboard.html
wagtail_localize_dashboard-0.1.0.dist-info/licenses/LICENSE
wagtail_localize_dashboard-0.1.0.dist-info/METADATA
wagtail_localize_dashboard-0.1.0.dist-info/WHEEL
wagtail_localize_dashboard-0.1.0.dist-info/top_level.txt
wagtail_localize_dashboard-0.1.0.dist-info/RECORD
