Metadata-Version: 2.4
Name: wagtail-localize-dashboard
Version: 0.1.0
Summary: Translation dashboard for wagtail-localize with caching
Author-email: Lincoln Loop <hello@lincolnloop.com>
License: MIT
Project-URL: Homepage, https://github.com/lincolnloop/wagtail-localize-dashboard
Project-URL: Documentation, https://wagtail-localize-dashboard.readthedocs.io
Project-URL: Repository, https://github.com/lincolnloop/wagtail-localize-dashboard
Project-URL: Bug Tracker, https://github.com/lincolnloop/wagtail-localize-dashboard/issues
Keywords: wagtail,localize,translation,i18n,l10n,dashboard
Classifier: Development Status :: 3 - Alpha
Classifier: Environment :: Web Environment
Classifier: Framework :: Django
Classifier: Framework :: Django :: 4.2
Classifier: Framework :: Django :: 5.0
Classifier: Framework :: Wagtail
Classifier: Framework :: Wagtail :: 5
Classifier: Framework :: Wagtail :: 6
Classifier: Intended Audience :: Developers
Classifier: License :: OSI Approved :: MIT License
Classifier: Operating System :: OS Independent
Classifier: Programming Language :: Python
Classifier: Programming Language :: Python :: 3
Classifier: Programming Language :: Python :: 3.10
Classifier: Programming Language :: Python :: 3.11
Classifier: Programming Language :: Python :: 3.12
Classifier: Programming Language :: Python :: 3.13
Classifier: Programming Language :: Python :: 3.14
Classifier: Topic :: Internet :: WWW/HTTP
Classifier: Topic :: Internet :: WWW/HTTP :: Dynamic Content
Classifier: Topic :: Software Development :: Internationalization
Classifier: Topic :: Software Development :: Localization
Requires-Python: >=3.10
License-File: LICENSE
Requires-Dist: Django>=4.2
Requires-Dist: Wagtail>=5.2
Requires-Dist: wagtail-localize>=1.8
Provides-Extra: test
Requires-Dist: pytest>=7.0; extra == "test"
Requires-Dist: pytest-django>=4.5; extra == "test"
Requires-Dist: pytest-cov>=4.0; extra == "test"
Provides-Extra: accessibility
Requires-Dist: selenium>=4.0; extra == "accessibility"
Requires-Dist: selenium-axe-python>=2.1; extra == "accessibility"
Provides-Extra: dev
Requires-Dist: pytest>=7.0; extra == "dev"
Requires-Dist: pytest-django>=4.5; extra == "dev"
Requires-Dist: pytest-cov>=4.0; extra == "dev"
Requires-Dist: black>=23.0; extra == "dev"
Requires-Dist: flake8>=6.0; extra == "dev"
Requires-Dist: isort>=5.12; extra == "dev"
Requires-Dist: mypy>=1.0; extra == "dev"
Requires-Dist: selenium>=4.0; extra == "dev"
Requires-Dist: selenium-axe-python>=2.1; extra == "dev"
Provides-Extra: docs
Requires-Dist: mkdocs>=1.5; extra == "docs"
Requires-Dist: mkdocs-material>=9.0; extra == "docs"
Requires-Dist: mkdocstrings[python]>=0.24; extra == "docs"
Dynamic: license-file
